LICENSE
README.md
setup.cfg
setup.py
gitlabform/__init__.py
gitlabform/constants.py
gitlabform/output.py
gitlabform/run.py
gitlabform/util.py
gitlabform/configuration/__init__.py
gitlabform/configuration/common.py
gitlabform/configuration/core.py
gitlabform/configuration/groups.py
gitlabform/configuration/projects.py
gitlabform/configuration/transform.py
gitlabform/gitlab/__init__.py
gitlabform/gitlab/branches.py
gitlabform/gitlab/commits.py
gitlabform/gitlab/core.py
gitlabform/gitlab/group_badges.py
gitlabform/gitlab/group_ldap_links.py
gitlabform/gitlab/group_saml_links.py
gitlabform/gitlab/group_variables.py
gitlabform/gitlab/groups.py
gitlabform/gitlab/integrations.py
gitlabform/gitlab/members.py
gitlabform/gitlab/merge_requests.py
gitlabform/gitlab/pipelines.py
gitlabform/gitlab/project_badges.py
gitlabform/gitlab/project_deploy_keys.py
gitlabform/gitlab/project_merge_requests_approvals.py
gitlabform/gitlab/project_protected_environments.py
gitlabform/gitlab/projects.py
gitlabform/gitlab/repositories.py
gitlabform/gitlab/resource_groups.py
gitlabform/gitlab/schedules.py
gitlabform/gitlab/tags.py
gitlabform/gitlab/users.py
gitlabform/gitlab/variables.py
gitlabform/lists/__init__.py
gitlabform/lists/filter.py
gitlabform/lists/groups.py
gitlabform/lists/projects.py
gitlabform/processors/__init__.py
gitlabform/processors/abstract_processor.py
gitlabform/processors/defining_keys.py
gitlabform/processors/multiple_entities_processor.py
gitlabform/processors/single_entity_processor.py
gitlabform/processors/group/__init__.py
gitlabform/processors/group/group_badges_processor.py
gitlabform/processors/group/group_ldap_links_processor.py
gitlabform/processors/group/group_members_processor.py
gitlabform/processors/group/group_saml_links_processor.py
gitlabform/processors/group/group_settings_processor.py
gitlabform/processors/group/group_variables_processor.py
gitlabform/processors/project/__init__.py
gitlabform/processors/project/badges_processor.py
gitlabform_ytt.egg-info/PKG-INFO
gitlabform_ytt.egg-info/SOURCES.txt
gitlabform_ytt.egg-info/dependency_links.txt
gitlabform_ytt.egg-info/entry_points.txt
gitlabform_ytt.egg-info/requires.txt
gitlabform_ytt.egg-info/top_level.txt
