Metadata-Version: 2.1
Name: gitlabform-ytt
Version: 3.7.0a5
Summary: 🏗 Specialized configuration as a code tool for GitLab projects, groups and more using hierarchical configuration written in YAML. Forked changes pending inclusion in Gitlabform
Home-page: https://gitlabform.github.io/gitlabform
Author: Greg Dubicki and Contributors
Keywords: cli,yaml,gitlab,configuration-as-code
Classifier: Programming Language :: Python :: 3.7
Classifier: Programming Language :: Python :: 3.8
Classifier: Programming Language :: Python :: 3.9
Classifier: Programming Language :: Python :: 3.10
Classifier: Programming Language :: Python :: 3.11
Classifier: Development Status :: 5 - Production/Stable
Classifier: Intended Audience :: Information Technology
Classifier: Intended Audience :: System Administrators
Classifier: License :: OSI Approved :: MIT License
Classifier: Operating System :: POSIX :: Linux
Classifier: Operating System :: MacOS
Classifier: Operating System :: Microsoft :: Windows
Classifier: Topic :: Software Development :: Version Control :: Git
Requires-Python: >=3.7.0
Provides-Extra: test
Provides-Extra: docs
License-File: LICENSE
